typing_json/__init__.py
typing_json/decoding.py
typing_json/encoding.py
typing_json/py.typed
typing_json/typechecking.py
typing_json-0.1.3.dist-info/LICENSE
typing_json-0.1.3.dist-info/METADATA
typing_json-0.1.3.dist-info/WHEEL
typing_json-0.1.3.dist-info/top_level.txt
typing_json-0.1.3.dist-info/RECORD
