Metadata-Version: 2.1
Name: typing-json
Version: 0.1.3
Summary: Type-aware Python JSON serialization and validation.
Home-page: https://github.com/sg495/typing-json
Author: sg495
Author-email: sg495@users.noreply.github.com
License: UNKNOWN
Platform: UNKNOWN
Classifier: Programming Language :: Python :: 3.7
Classifier: License :: OSI Approved :: MIT License
Classifier: Operating System :: OS Independent
Classifier: Development Status :: 4 - Beta
Classifier: Natural Language :: English
Classifier: Typing :: Typed
Requires-Dist: typing-extensions
